samaker/__init__.py
samaker/_constants.py
samaker/_log.py
samaker/_printer.py
samaker/_samaker.py
samaker/cache.py
samaker/cli.py
samaker/exceptions.py
samaker/field.py
samaker/fixture.py
samaker/hook_manager.py
samaker/log.py
samaker/make.py
samaker/make_api.py
samaker/make_testcase.py
samaker/models.py
samaker/param_types.py
samaker/path.py
samaker/report.py
samaker/runner.py
samaker/samaker.py
samaker/scaffold.py
samaker/swagger2yaml.py
samaker/template.py
samaker/yaml2case.py
samaker/base/__init__.py
samaker/base/base_api.py
samaker/base/base_testcase.py
samaker/database/__init__.py
samaker/database/mysql.py
samaker/database/sqlite.py
samaker/extension/__init__.py
samaker/extension/har_parse/__init__.py
samaker/extension/har_parse/har_parse.py
samaker/extension/recording/__init__.py
samaker/extension/recording/addons.py
samaker/extension/recording/recording.py
samaker/extension/retry/__init__.py
samaker/extension/retry/retry.py
samaker/html/AOReporter_logo.png
samaker/html/heading.html
samaker/html/report.html
samaker/html/template.html
samaker/send_msg/__init__.py
samaker/send_msg/wechat.py
samaker/utils/__init__.py
samaker/utils/gen_allure_report.py
samaker/utils/utils.py
samaker-1.2.2.dist-info/LICENSE
samaker-1.2.2.dist-info/METADATA
samaker-1.2.2.dist-info/WHEEL
samaker-1.2.2.dist-info/entry_points.txt
samaker-1.2.2.dist-info/top_level.txt
samaker-1.2.2.dist-info/RECORD
