Metadata-Version: 2.1
Name: samaker
Version: 1.2.2
Summary: A TestCase maker package
Author: wenbin Shi
Author-email: shiwenbin1617@gmail.com
Classifier: Programming Language :: Python :: 3
Classifier: License :: OSI Approved :: MIT License
Classifier: Operating System :: OS Independent
Requires-Python: >=3.6
License-File: LICENSE
